neurodeckit/__init__.py
neurodeckit/analysis/__init__.py
neurodeckit/analysis/meat_anaysis.py
neurodeckit/analysis/meta_anaysis.py
neurodeckit/anaysis/__init__.py
neurodeckit/anaysis/anaysis.py
neurodeckit/deep_learning/__init__.py
neurodeckit/deep_learning/base.py
neurodeckit/deep_learning/convca.py
neurodeckit/deep_learning/cspnet.py
neurodeckit/deep_learning/deep4.py
neurodeckit/deep_learning/deepnet.py
neurodeckit/deep_learning/dl_classifier.py
neurodeckit/deep_learning/eegnet.py
neurodeckit/deep_learning/eegnetv4.py
neurodeckit/deep_learning/fbcnet.py
neurodeckit/deep_learning/format_data.py
neurodeckit/deep_learning/functional.py
neurodeckit/deep_learning/guney_net.py
neurodeckit/deep_learning/lmda_net.py
neurodeckit/deep_learning/shallow_fbcsp.py
neurodeckit/deep_learning/shallownet.py
neurodeckit/ensemble_learning/__init__.py
neurodeckit/ensemble_learning/adaboost.py
neurodeckit/ensemble_learning/base.py
neurodeckit/ensemble_learning/demo_Catboost.py
neurodeckit/ensemble_learning/demo_LightGBM.py
neurodeckit/ensemble_learning/demo_XGboost.py
neurodeckit/ensemble_learning/el_classifier.py
neurodeckit/ensemble_learning/rave.py
neurodeckit/loaddata/__init__.py
neurodeckit/loaddata/change_dataset_download_path.py
neurodeckit/loaddata/data2mat.py
neurodeckit/loaddata/dataset_mi.py
neurodeckit/loaddata/liu2024.py
neurodeckit/loaddata/pan2023.py
neurodeckit/loaddata/wrcc_bcic_mi.py
neurodeckit/machine_learning/__init__.py
neurodeckit/machine_learning/alglist2.py
neurodeckit/machine_learning/base.py
neurodeckit/machine_learning/cca.py
neurodeckit/machine_learning/classifier.py
neurodeckit/machine_learning/csp.py
neurodeckit/machine_learning/ctssp.py
neurodeckit/machine_learning/dsp.py
neurodeckit/machine_learning/feature_select.py
neurodeckit/machine_learning/ml_classifier.py
neurodeckit/machine_learning/rpa.py
neurodeckit/machine_learning/sblest.py
neurodeckit/machine_learning/ts.py
neurodeckit/pre_processing/__init__.py
neurodeckit/pre_processing/base.py
neurodeckit-0.1.0.dist-info/licenses/LICENSE
neurodeckit-0.1.0.dist-info/METADATA
neurodeckit-0.1.0.dist-info/WHEEL
neurodeckit-0.1.0.dist-info/top_level.txt
neurodeckit-0.1.0.dist-info/RECORD
