Metadata-Version: 2.4
Name: neurodeckit
Version: 0.1.0
Summary: Full chain toolkit for EEG signal decoding
Home-page: https://github.com/PLC-TJU/NeuroDecKit
Author: LC.Pan
Author-email: panlincong@tju.edu.cn
Keywords: python,package
Classifier: Programming Language :: Python :: 3
Classifier: License :: OSI Approved :: BSD License
Classifier: Operating System :: OS Independent
License-File: LICENSE
Requires-Dist: braindecode
Requires-Dist: einops
Requires-Dist: geoopt
Requires-Dist: h5py
Requires-Dist: joblib
Requires-Dist: mne
Requires-Dist: numpy
Requires-Dist: pandas
Requires-Dist: pooch
Requires-Dist: psutil
Requires-Dist: pynvml
Requires-Dist: pyriemann==0.6
Requires-Dist: scikit_learn
Requires-Dist: scipy
Requires-Dist: skorch
Requires-Dist: statsmodels
Requires-Dist: torch
Requires-Dist: torchsummary
Dynamic: author
Dynamic: author-email
Dynamic: classifier
Dynamic: description
Dynamic: description-content-type
Dynamic: home-page
Dynamic: keywords
Dynamic: license-file
Dynamic: requires-dist
Dynamic: summary
